hashtrade-1.1.0.dist-info/licenses/LICENSE
server/__init__.py
server/_version.py
server/main.py
server/data/history.jsonl
server/tools/__init__.py
server/tools/history.py
server/tools/interface.py
server/tools/use_ccxt.py
hashtrade-1.1.0.dist-info/METADATA
hashtrade-1.1.0.dist-info/WHEEL
hashtrade-1.1.0.dist-info/entry_points.txt
hashtrade-1.1.0.dist-info/top_level.txt
hashtrade-1.1.0.dist-info/RECORD
