Metadata-Version: 2.4
Name: hashtrade
Version: 1.1.0
Summary: A real-time cryptocurrency trading dashboard powered by AI agents with multi-exchange support
Author-email: Mert Ozbas <mertozbas@gmail.com>
Maintainer-email: Mert Ozbas <mertozbas@gmail.com>
License: Apache-2.0
Project-URL: Homepage, https://mertozbas.github.io/hashtrade/
Project-URL: Repository, https://github.com/mertozbas/hashtrade
Project-URL: Documentation, https://github.com/mertozbas/hashtrade#readme
Project-URL: Issues, https://github.com/mertozbas/hashtrade/issues
Project-URL: Changelog, https://github.com/mertozbas/hashtrade/releases
Project-URL: Dashboard, https://mertozbas.github.io/hashtrade/
Project-URL: PyPI, https://pypi.org/project/hashtrade/
Keywords: cryptocurrency,trading,dashboard,ai,agent,ccxt,websocket
Classifier: Development Status :: 4 - Beta
Classifier: Intended Audience :: Developers
Classifier: Intended Audience :: Financial and Insurance Industry
Classifier: License :: OSI Approved :: Apache Software License
Classifier: Operating System :: OS Independent
Classifier: Programming Language :: Python :: 3
Classifier: Programming Language :: Python :: 3.11
Classifier: Programming Language :: Python :: 3.12
Classifier: Topic :: Office/Business :: Financial :: Investment
Classifier: Topic :: Software Development :: Libraries :: Python Modules
Classifier: Topic :: Internet :: WWW/HTTP :: Dynamic Content
Requires-Python: >=3.11
License-File: LICENSE
Requires-Dist: strands-agents
Requires-Dist: strands-agents[anthropic]
Requires-Dist: strands-agents[openai]
Requires-Dist: strands-agents[ollama]
Requires-Dist: strands-agents-tools
Requires-Dist: websockets>=12.0
Requires-Dist: ccxt>=4.0.0
Provides-Extra: ollama
Dynamic: license-file
